megafish/__init__.py
megafish/config.py
megafish/decode.py
megafish/load.py
megafish/napari.py
megafish/process.py
megafish/register.py
megafish/segment.py
megafish/seqfish.py
megafish/seqif.py
megafish/tif.py
megafish/utils.py
megafish/view.py
megafish-0.1.2.dist-info/LICENSE
megafish-0.1.2.dist-info/METADATA
megafish-0.1.2.dist-info/WHEEL
megafish-0.1.2.dist-info/top_level.txt
megafish-0.1.2.dist-info/RECORD
