Metadata-Version: 2.1
Name: megafish
Version: 0.1.2
Summary: Multi-omics Extensible GPU-Accelerated FISH analysis framework
Author-email: Yuma Ito <yumaitou@outlook.com>
License: BSD 3-Clause License
Classifier: Programming Language :: Python :: 3.11
Requires-Python: <3.12,>=3.11
License-File: LICENSE
Requires-Dist: numpy
Requires-Dist: pandas
Requires-Dist: matplotlib
Requires-Dist: dask
Requires-Dist: xarray
Requires-Dist: zarr
Requires-Dist: scikit-image
Requires-Dist: scikit-learn
Requires-Dist: tifffile
Requires-Dist: scipy
Requires-Dist: napari[all]
Requires-Dist: imaris-ims-file-reader
Provides-Extra: cpu
Requires-Dist: numpy; extra == "cpu"
